ooputil/__init__.py
ooputil/models/__init__.py
ooputil/models/interfaces.py
ooputil-0.2.4.dist-info/LICENSE
ooputil-0.2.4.dist-info/METADATA
ooputil-0.2.4.dist-info/WHEEL
ooputil-0.2.4.dist-info/top_level.txt
ooputil-0.2.4.dist-info/RECORD
