Metadata-Version: 2.2
Name: ooputil
Version: 0.2.4
Summary: Library for OOP utilities
Author: Rafael da Rocha Ferreira
Author-email: Rafael da Rocha Ferreira <programadorlhama@gmail.com>
License: MIT
Project-URL: Homepage, https://github.com/programadorLhama/ooputil.git
Project-URL: Repository, https://github.com/programadorLhama/ooputil.git
Requires-Python: >=3.6
License-File: LICENSE
Dynamic: author
Dynamic: requires-python
